odoo/addons/l10n_br_nfse_issnet/README.rst
odoo/addons/l10n_br_nfse_issnet/__init__.py
odoo/addons/l10n_br_nfse_issnet/__manifest__.py
odoo/addons/l10n_br_nfse_issnet/constants/issnet.py
odoo/addons/l10n_br_nfse_issnet/demo/city_taxation_code_demo.xml
odoo/addons/l10n_br_nfse_issnet/i18n/l10n_br_nfse_issnet.pot
odoo/addons/l10n_br_nfse_issnet/models/__init__.py
odoo/addons/l10n_br_nfse_issnet/models/l10n_br_fiscal_document.py
odoo/addons/l10n_br_nfse_issnet/models/res_company.py
odoo/addons/l10n_br_nfse_issnet/readme/CONFIGURE.rst
odoo/addons/l10n_br_nfse_issnet/readme/CONTRIBUTORS.rst
odoo/addons/l10n_br_nfse_issnet/readme/CREDITS.rst
odoo/addons/l10n_br_nfse_issnet/readme/DESCRIPTION.rst
odoo/addons/l10n_br_nfse_issnet/readme/HISTORY.rst
odoo/addons/l10n_br_nfse_issnet/readme/INSTALL.rst
odoo/addons/l10n_br_nfse_issnet/readme/ROADMAP.rst
odoo/addons/l10n_br_nfse_issnet/readme/USAGE.rst
odoo/addons/l10n_br_nfse_issnet/static/description/banner.png
odoo/addons/l10n_br_nfse_issnet/static/description/icon.png
odoo/addons/l10n_br_nfse_issnet/static/description/index.html
odoo/addons/l10n_br_nfse_issnet/tests/__init__.py
odoo/addons/l10n_br_nfse_issnet/tests/test_fiscal_document_nfse_issnet.py
odoo/addons/l10n_br_nfse_issnet/tests/nfse/001_50_nfse.xml
odoo12_addon_l10n_br_nfse_issnet-12.0.3.1.0.dist-info/METADATA
odoo12_addon_l10n_br_nfse_issnet-12.0.3.1.0.dist-info/WHEEL
odoo12_addon_l10n_br_nfse_issnet-12.0.3.1.0.dist-info/top_level.txt
odoo12_addon_l10n_br_nfse_issnet-12.0.3.1.0.dist-info/RECORD
